{
    "compiled": {
        "names": [
            "hybrid",
            "set0",
            "set10",
            "set20",
            "set21",
            "set30",
            "set40",
            "set50",
            "set63",
            "set70"
        ],
        "paths": [
            "data/hybrid/hybrid.h5",
            "data/set0/set0.h5",
            "data/set10/set10.h5",
            "data/set20/set20.h5",
            "data/set21/set21.h5",
            "data/set30/set30.h5",
            "data/set40/set40.h5",
            "data/set50/set50.h5",
            "data/set63/set63.h5",
            "data/set70/set70.h5"
        ]
    },
    "uncompiled": {
        "names": [
            "hybrid",
            "set0",
            "set10",
            "set20",
            "set21",
            "set30",
            "set40",
            "set50",
            "set63",
            "set70"
        ],
        "paths": [
            "data/raw/hybrid.zip",
            "data/raw/set0.zip",
            "data/raw/set10.zip",
            "data/raw/set20.zip",
            "data/raw/set21.zip",
            "data/raw/set30.zip",
            "data/raw/set40.zip",
            "data/raw/set50.zip",
            "data/raw/set63.zip",
            "data/raw/set70.zip"
        ]
    }
}